django_carch/__init__.py
django_carch/__main__.py
django_carch/bootstrap.md
django_carch/core.py
django_carch-1.0.4.dist-info/licenses/LICENSE
django_carch-1.0.4.dist-info/METADATA
django_carch-1.0.4.dist-info/WHEEL
django_carch-1.0.4.dist-info/entry_points.txt
django_carch-1.0.4.dist-info/top_level.txt
django_carch-1.0.4.dist-info/RECORD
