Metadata-Version: 2.4
Name: django-carch
Version: 1.0.4
Summary: Générateur de projet Django Clean Architecture avec support DevOps
Home-page: https://github.com/daniel10027/django-cleanarch-starter/
Author: Jean Marie Daniel Vianney Guedegbe
Classifier: Development Status :: 5 - Production/Stable
Classifier: Intended Audience :: Developers
Classifier: Topic :: Software Development :: Code Generators
Classifier: License :: OSI Approved :: MIT License
Classifier: Programming Language :: Python :: 3
Classifier: Framework :: Django
Classifier: Operating System :: OS Independent
Requires-Python: >=3.8
License-File: LICENSE
Dynamic: author
Dynamic: classifier
Dynamic: description
Dynamic: description-content-type
Dynamic: home-page
Dynamic: license-file
Dynamic: requires-python
Dynamic: summary
